pwb_jupyterlab/.gitignore
pwb_jupyterlab/__init__.py
pwb_jupyterlab/_version.py
pwb_jupyterlab/constants.py
pwb_jupyterlab/handlers.py
pwb_jupyterlab/network.py
pwb_jupyterlab/process.py
pwb_jupyterlab/proxiedServersProvider.py
pwb_jupyterlab/tests/__init__.py
pwb_jupyterlab/tests/test_handlers.py
pwb_jupyterlab/tests/test_network.py
pwb_jupyterlab/tests/resources/.gitignore
pwb_jupyterlab/tests/resources/basics-jupyter.ipynb
pwb_jupyterlab/tests/resources/hello.qmd
pwb_jupyterlab-1.1.23.data/data/etc/jupyter/jupyter_server_config.d/pwb_jupyterlab.json
pwb_jupyterlab-1.1.23.data/data/etc/jupyter/jupyter_server_config.d/workbench_jupyterlab.json
pwb_jupyterlab-1.1.23.data/data/share/jupyter/labextensions/pwb_jupyterlab/build_log.json
pwb_jupyterlab-1.1.23.data/data/share/jupyter/labextensions/pwb_jupyterlab/package.json
pwb_jupyterlab-1.1.23.data/data/share/jupyter/labextensions/pwb_jupyterlab/schemas/pwb_jupyterlab/package.json.orig
pwb_jupyterlab-1.1.23.data/data/share/jupyter/labextensions/pwb_jupyterlab/schemas/pwb_jupyterlab/plugin.json
pwb_jupyterlab-1.1.23.data/data/share/jupyter/labextensions/pwb_jupyterlab/static/lib_index_js.ea07e9e03c92ff760901.js
pwb_jupyterlab-1.1.23.data/data/share/jupyter/labextensions/pwb_jupyterlab/static/lib_index_js.ea07e9e03c92ff760901.js.map
pwb_jupyterlab-1.1.23.data/data/share/jupyter/labextensions/pwb_jupyterlab/static/remoteEntry.5d7308ec4af09db02d14.js
pwb_jupyterlab-1.1.23.data/data/share/jupyter/labextensions/pwb_jupyterlab/static/remoteEntry.5d7308ec4af09db02d14.js.map
pwb_jupyterlab-1.1.23.data/data/share/jupyter/labextensions/pwb_jupyterlab/static/style.js
pwb_jupyterlab-1.1.23.data/data/share/jupyter/labextensions/pwb_jupyterlab/static/style_index_js.6ff6ba1bc54f497e4f17.js
pwb_jupyterlab-1.1.23.data/data/share/jupyter/labextensions/pwb_jupyterlab/static/style_index_js.6ff6ba1bc54f497e4f17.js.map
pwb_jupyterlab-1.1.23.data/data/share/jupyter/labextensions/pwb_jupyterlab/install.json
pwb_jupyterlab-1.1.23.dist-info/METADATA
pwb_jupyterlab-1.1.23.dist-info/WHEEL
pwb_jupyterlab-1.1.23.dist-info/RECORD
