Metadata-Version: 2.4
Name: pwb_jupyterlab
Version: 1.1.23
Dynamic: Keywords
Summary: Enhance experience of running JupyterLab 4 in Posit Workbench.
Project-URL: Homepage, https://docs.posit.co/ide/server-pro/user/jupyter-lab/guide/posit-workbench-extension.html
Project-URL: Repository, https://github.com/rstudio/rstudio-pro/tree/main/src/cpp/session/workspaces/pwb-jupyterlab/extensions
Author: Posit Software, PBC
Classifier: Framework :: Jupyter
Classifier: Framework :: Jupyter :: JupyterLab
Classifier: Framework :: Jupyter :: JupyterLab :: 4
Classifier: Framework :: Jupyter :: JupyterLab :: Extensions
Classifier: Framework :: Jupyter :: JupyterLab :: Extensions :: Prebuilt
Classifier: License :: OSI Approved :: BSD License
Classifier: Programming Language :: Python
Classifier: Programming Language :: Python :: 3
Classifier: Programming Language :: Python :: 3.8
Classifier: Programming Language :: Python :: 3.9
Classifier: Programming Language :: Python :: 3.10
Classifier: Programming Language :: Python :: 3.11
Classifier: Programming Language :: Python :: 3.12
Requires-Python: >=3.8
Requires-Dist: jupyter-server-proxy>=4.1.0
Requires-Dist: jupyter-server<3,>=2.0.1
Provides-Extra: test
Requires-Dist: coverage; extra == 'test'
Requires-Dist: pytest; extra == 'test'
Requires-Dist: pytest-asyncio; extra == 'test'
Requires-Dist: pytest-cov; extra == 'test'
Requires-Dist: pytest-jupyter[server]>=0.6.0; extra == 'test'
